rawphoto-0.4.1.dist-info/DESCRIPTION.rst
rawphoto-0.4.1.dist-info/WHEEL
rawphoto-0.4.1.dist-info/RECORD
rawphoto-0.4.1.dist-info/metadata.json
rawphoto-0.4.1.dist-info/METADATA
rawphoto-0.4.1.dist-info/top_level.txt
rawphoto/__init__.py
rawphoto/tiff.py
rawphoto/nef.py
rawphoto/raw.py
rawphoto/cr2.py
