Metadata-Version: 2.0
Name: rawphoto
Version: 0.4.1
Summary: Utilities for managing raw photos
Home-page: https://github.com/photoshell/rawphoto
Author: Sam Whited
Author-email: sam@samwhited.com
License: UNKNOWN
Keywords: encoding,images,photography
Platform: UNKNOWN
Classifier: Programming Language :: Python
Classifier: Programming Language :: Python :: 2
Classifier: Programming Language :: Python :: 2.7
Classifier: Programming Language :: Python :: 3
Classifier: Programming Language :: Python :: 3.3
Classifier: Programming Language :: Python :: 3.4
Classifier: Development Status :: 7 - Inactive
Classifier: Intended Audience :: Developers
Classifier: License :: OSI Approved :: MIT License
Classifier: License :: OSI Approved :: BSD License
Classifier: Operating System :: OS Independent
Classifier: Environment :: Other Environment
Classifier: Topic :: Software Development :: Libraries :: Python Modules
